pymixing.py
pymixing-0.9.3.dist-info/LICENSE
pymixing-0.9.3.dist-info/METADATA
pymixing-0.9.3.dist-info/WHEEL
pymixing-0.9.3.dist-info/top_level.txt
pymixing-0.9.3.dist-info/RECORD
