Metadata-Version: 2.1
Name: pymixing
Version: 0.9.3
Summary: A simple daw in python.
Home-page: https://github.com/JalleyLin/pymixing
Author: Lin
Author-email: linzichuqi@qq.com
License: MIT
Platform: UNKNOWN
Classifier: License :: OSI Approved :: MIT License
Classifier: Programming Language :: Python
Classifier: Programming Language :: Python :: 3
Classifier: Programming Language :: Python :: 3.6
Classifier: Programming Language :: Python :: Implementation :: CPython
Classifier: Programming Language :: Python :: Implementation :: PyPy
Requires-Python: >=3.6.0
License-File: LICENSE
Requires-Dist: numpy
Requires-Dist: librosa
Requires-Dist: pyloudnorm
Requires-Dist: soundfile
Requires-Dist: matplotlib
Requires-Dist: scipy
